color_plot/__init__.py
color_plot/core.py
color_plot-0.1.5.dist-info/LICENSE
color_plot-0.1.5.dist-info/METADATA
color_plot-0.1.5.dist-info/WHEEL
color_plot-0.1.5.dist-info/top_level.txt
color_plot-0.1.5.dist-info/RECORD
