Metadata-Version: 2.1
Name: color-plot
Version: 0.1.5
Summary: colorplot
Home-page: https://github.com/yusukeMuraki/color_plot
Author: Yusuke Muraki
Author-email: UNKNOWN
License: Copyright (c) 2017, Kenneth Reitz
Requires-Dist: numpy
Requires-Dist: pyshp
Requires-Dist: matplotlib
Requires-Dist: geopandas
